Usmap/BinaryReader.py
Usmap/Oodle.py
Usmap/__init__.py
Usmap/main.py
Usmap/Objects/FName.py
Usmap/Objects/FPropertyTag.py
Usmap/Objects/__init__.py
pyUsmap-1.1.3.dist-info/METADATA
pyUsmap-1.1.3.dist-info/WHEEL
pyUsmap-1.1.3.dist-info/top_level.txt
pyUsmap-1.1.3.dist-info/RECORD
