Metadata-Version: 2.1
Name: pyUsmap
Version: 1.1.3
Summary: .usmap file reader
Home-page: https://github.com/MinshuG/pyUsmap
Author: MinshuG
License: UNKNOWN
Platform: UNKNOWN
Classifier: Programming Language :: Python :: 3
Requires-Dist: Brotli
